Metadata-Version: 2.4
Name: math-lib-geometry-maksim
Version: 0.1.0
Summary: Библиотека для вычисления площадей геометрических фигур
Author-email: Maksim <maksimgubenin@mail.ru>
Requires-Python: >=3.12
Requires-Dist: setuptools<81.0.0,>=80.9.0
